framework/__init__.py
framework/base/__init__.py
framework/base/base.py
framework/reader/__init__.py
framework/reader/csv_reader.py
framework/transform/__init__.py
framework/transform/transform1.py
framework/transform/transform2.py
framework/transform/transform3.py
framework/transform/transform4.py
framework/transform/transform5.py
framework/transform/transform6.py
framework/transform/transform7.py
framework/transform/transform8.py
framework/writer/__init__.py
framework/writer/csv_writer.py
abn_amro_assessment_2024-0.0.5.dist-info/METADATA
abn_amro_assessment_2024-0.0.5.dist-info/WHEEL
abn_amro_assessment_2024-0.0.5.dist-info/top_level.txt
abn_amro_assessment_2024-0.0.5.dist-info/RECORD
